README.md
setup.py
vision_utils/__init__.py
vision_utils/boxutils.py
vision_utils/generic_utils.py
vision_utils_0.1.1.egg-info/PKG-INFO
vision_utils_0.1.1.egg-info/SOURCES.txt
vision_utils_0.1.1.egg-info/dependency_links.txt
vision_utils_0.1.1.egg-info/top_level.txt