Metadata-Version: 1.0
Name: vision-utils-0.1.1
Version: 0.1.1
Summary: miscellaneous utils for computer vision projects
Home-page: https://github.com/rosenfeldamir/vision_utils
Author: Amir Rosenfeld
Author-email: amir.rosenfeld@gmail.com
License: MIT
Platform: UNKNOWN
